Metadata-Version: 2.4
Name: superduper-framework
Version: 0.10.0
Summary: Build compositional and declarative AI applications and agents
Maintainer-email: "superduper.io, Inc." <opensource@superduper.com>
License: 
Project-URL: homepage, https://superduper.io
Project-URL: documentation, https://docs.superduper.io/docs/intro
Project-URL: source, https://github.com/superduper-io/superduper
Keywords: databases,mongodb,data-science,machine-learning,mlops,vector-database,ai
Classifier: Development Status :: 3 - Alpha
Classifier: Environment :: GPU :: NVIDIA CUDA
Classifier: License :: OSI Approved :: Apache Software License
Classifier: Operating System :: OS Independent
Classifier: Programming Language :: Python :: 3.10
Classifier: Programming Language :: Python :: 3.11
Classifier: Programming Language :: Python :: Implementation :: CPython
Classifier: Topic :: Database
Classifier: Topic :: Scientific/Engineering :: Artificial Intelligence
Classifier: Topic :: Software Development :: Libraries :: Python Modules
Classifier: Typing :: Typed
Requires-Python: >=3.10
License-File: LICENSE
Requires-Dist: boto3>=1.16
Requires-Dist: dill>=0.3.6
Requires-Dist: loguru>=0.7.2
Requires-Dist: loki-logger-handler==1.0.0
Requires-Dist: networkx>=2.8.8
Requires-Dist: requests>=2.22
Requires-Dist: tqdm>=4.64.1
Requires-Dist: typer>=0.7.0
Requires-Dist: pydantic>=1
Requires-Dist: pygments
Requires-Dist: numpy>=1.24.3
Requires-Dist: overrides>=7
Requires-Dist: tenacity<=8.2.3,>=8.1.0
Requires-Dist: packaging
Requires-Dist: pandas
Requires-Dist: prettytable
Requires-Dist: python-dotenv
Requires-Dist: PyYAML>=6.0.0
Requires-Dist: uvicorn>=0.24.0
Requires-Dist: fastapi>=0.103.2
Requires-Dist: pyyaml
Requires-Dist: ruamel.yaml>=0.18
Requires-Dist: python-magic
Requires-Dist: apscheduler
Requires-Dist: python-multipart>=0.0.9
Requires-Dist: httpx
Requires-Dist: toml
Requires-Dist: papermill>=2.6.0
Requires-Dist: jupyter
Provides-Extra: test
Requires-Dist: scikit-learn>=1.1.3; extra == "test"
Requires-Dist: pre-commit; extra == "test"
Requires-Dist: black==25.1.0; extra == "test"
Requires-Dist: ruff==0.4.4; extra == "test"
Requires-Dist: mypy==1.15.0; extra == "test"
Requires-Dist: types-PyYAML; extra == "test"
Requires-Dist: types-requests; extra == "test"
Requires-Dist: interrogate; extra == "test"
Requires-Dist: pytest; extra == "test"
Requires-Dist: pytest-cov; extra == "test"
Requires-Dist: nbval>=0.10.0; extra == "test"
Dynamic: license-file
